README.md
setup.py
azkaban_cli/__init__.py
azkaban_cli/__version__.py
azkaban_cli/api.py
azkaban_cli/azkaban.py
azkaban_cli/azkaban_cli.py
azkaban_cli/exceptions.py
azkaban_cli.egg-info/PKG-INFO
azkaban_cli.egg-info/SOURCES.txt
azkaban_cli.egg-info/dependency_links.txt
azkaban_cli.egg-info/entry_points.txt
azkaban_cli.egg-info/requires.txt
azkaban_cli.egg-info/top_level.txt
azkaban_cli/tests/__init__.py
azkaban_cli/tests/test_azkaban/__init__.py
azkaban_cli/tests/test_azkaban/test_add_permission.py
azkaban_cli/tests/test_azkaban/test_change_permission.py
azkaban_cli/tests/test_azkaban/test_create.py
azkaban_cli/tests/test_azkaban/test_delete.py
azkaban_cli/tests/test_azkaban/test_execute.py
azkaban_cli/tests/test_azkaban/test_fetch_flow_execution.py
azkaban_cli/tests/test_azkaban/test_fetch_flows.py
azkaban_cli/tests/test_azkaban/test_fetch_jobs_from_flow.py
azkaban_cli/tests/test_azkaban/test_fetch_projects.py
azkaban_cli/tests/test_azkaban/test_fetch_schedule.py
azkaban_cli/tests/test_azkaban/test_fetch_sla.py
azkaban_cli/tests/test_azkaban/test_login.py
azkaban_cli/tests/test_azkaban/test_remove_permission.py
azkaban_cli/tests/test_azkaban/test_schedule.py
azkaban_cli/tests/test_azkaban/test_unschedule.py
azkaban_cli/tests/test_azkaban/test_upload.py