Metadata-Version: 1.1
Name: azkaban-cli
Version: 0.9.2
Summary: Azkaban CLI
Home-page: UNKNOWN
Author: Gustavo Alves
Author-email: gustavo.alves@corp.globo.com
License: UNKNOWN
Platform: UNKNOWN
Classifier: Development Status :: 3 - Alpha
Classifier: Environment :: Console
Classifier: Intended Audience :: Developers
Classifier: Operating System :: POSIX
Classifier: Programming Language :: Python :: 3.7
